mplEasyAnimate/__init__.py
mplEasyAnimate/animate.py
mplEasyAnimate-0.6.1.dist-info/LICENSE.md
mplEasyAnimate-0.6.1.dist-info/METADATA
mplEasyAnimate-0.6.1.dist-info/WHEEL
mplEasyAnimate-0.6.1.dist-info/top_level.txt
mplEasyAnimate-0.6.1.dist-info/RECORD
